nindex/__init__.py
nindex/index.py
nindex-1.0.0.dist-info/LICENSE
nindex-1.0.0.dist-info/METADATA
nindex-1.0.0.dist-info/WHEEL
nindex-1.0.0.dist-info/top_level.txt
nindex-1.0.0.dist-info/zip-safe
nindex-1.0.0.dist-info/RECORD
