Metadata-Version: 2.1
Name: nindex
Version: 1.0.0
Summary: nindex
Home-page: UNKNOWN
Author: Natalie Fearnley
Author-email: nfearnley@gmail.com
License: MIT
Project-URL: Source, https://github.com/nindex/nygame
Project-URL: Tracker, https://github.com/nindex/nygame/issues
Keywords: index bisect
Platform: any
Classifier: License :: OSI Approved :: MIT License
Classifier: Operating System :: OS Independent
Classifier: Programming Language :: Python :: 3
Requires-Python: >=3.8
License-File: LICENSE
Provides-Extra: dev
Requires-Dist: autopep8 (==1.5.7) ; extra == 'dev'
Requires-Dist: flake8 (==3.9.2) ; extra == 'dev'
Requires-Dist: pytest (==6.2.4) ; extra == 'dev'
